celine/utils/__init__.py
celine/utils/admin/__init__.py
celine/utils/admin/clients.py
celine/utils/admin/setup/__init__.py
celine/utils/admin/setup/keycloak_setup.py
celine/utils/admin/setup/superset_setup.py
celine/utils/cli/__init__.py
celine/utils/cli/app.py
celine/utils/cli/main.py
celine/utils/cli/utils.py
celine/utils/cli/commands/__init__.py
celine/utils/cli/commands/admin/__init__.py
celine/utils/cli/commands/admin/admin.py
celine/utils/cli/commands/admin/app.py
celine/utils/cli/commands/admin/setup.py
celine/utils/cli/commands/admin/keycloak/__init__.py
celine/utils/cli/commands/admin/keycloak/accounts.py
celine/utils/cli/commands/admin/keycloak/app.py
celine/utils/cli/commands/admin/keycloak/clients.py
celine/utils/cli/commands/governance/__init__.py
celine/utils/cli/commands/governance/app.py
celine/utils/cli/commands/governance/generate.py
celine/utils/cli/commands/pipeline/__init__.py
celine/utils/cli/commands/pipeline/app.py
celine/utils/cli/commands/pipeline/init.py
celine/utils/cli/commands/pipeline/run.py
celine/utils/common/__init__.py
celine/utils/common/colorlog.py
celine/utils/common/logger.py
celine/utils/common/mqtt.py
celine/utils/common/superset.py
celine/utils/common/utils.py
celine/utils/common/config/__init__.py
celine/utils/common/config/mqtt.py
celine/utils/common/config/settings.py
celine/utils/common/config/superset.py
celine/utils/common/keycloak/__init__.py
celine/utils/common/keycloak/config.py
celine/utils/common/keycloak/keycloak_admin.py
celine/utils/common/keycloak/keycloak_client.py
celine/utils/datasets/__init__.py
celine/utils/datasets/__main__.py
celine/utils/datasets/client.py
celine/utils/datasets/config.py
celine/utils/pipelines/__init__.py
celine/utils/pipelines/const.py
celine/utils/pipelines/governance.py
celine/utils/pipelines/pipeline.py
celine/utils/pipelines/pipeline_config.py
celine/utils/pipelines/pipeline_prefect.py
celine/utils/pipelines/pipeline_result.py
celine/utils/pipelines/pipeline_runner.py
celine_utils-1.4.4.dist-info/licenses/LICENSE
celine_utils-1.4.4.dist-info/METADATA
celine_utils-1.4.4.dist-info/WHEEL
celine_utils-1.4.4.dist-info/entry_points.txt
celine_utils-1.4.4.dist-info/top_level.txt
celine_utils-1.4.4.dist-info/RECORD
