Metadata-Version: 2.4
Name: celine-utils
Version: 1.4.4
Summary: CELINE utils
Requires-Python: >=3.11
License-File: LICENSE
Requires-Dist: bcrypt>=4.3.0
Requires-Dist: openlineage-python>=1.37.0
Requires-Dist: paho-mqtt>=2.1.0
Requires-Dist: pandas>=2.3.2
Requires-Dist: psycopg2-binary>=2.9.10
Requires-Dist: pydantic>=2.11.7
Requires-Dist: pydantic-settings>=2.10.1
Requires-Dist: python-dotenv>=1.1.1
Requires-Dist: python-keycloak>=5.8.1
Requires-Dist: requests>=2.32.5
Requires-Dist: sqlalchemy>=2.0.43
Requires-Dist: typer>=0.16.1
Requires-Dist: dbt-core>=1.10.10
Requires-Dist: dbt-postgres>=1.9.1
Requires-Dist: prefect-dbt>=0.7.6
Requires-Dist: meltano>=3.9.1
Requires-Dist: prefect>=3.4.19
Dynamic: license-file
